{"Response": "Success", "Message": "", "HasWarning": false, "Type": 100, "RateLimit": {}, "Data": {"RAW": {"EOS": {"BNB": {"BID": ".2073", "ASK": ".2077"}, "BTC": {"BID": ".0007632", "ASK": ".0007633"}, "ETH": {"BID": ".02594", "ASK": ".025964"}, "USDT": {"BID": "7.0441", "ASK": "7.046"}, "USDC": {"BID": "7.0535", "ASK": "7.078"}, "PAX": {"BID": "7.0535", "ASK": "7.07"}, "TUSD": {"BID": "7.057", "ASK": "7.0757"}}}, "DISPLAY": {"EOS": {"BNB": {"BID": "BNB 0.2073", "ASK": "BNB 0.2077"}, "BTC": {"BID": "\u0243 0.0007632", "ASK": "\u0243 0.0007633"}, "ETH": {"BID": "\u039e 0.02594", "ASK": "\u039e 0.02596"}, "USDT": {"BID": "\u20ae 7.04", "ASK": "\u20ae 7.05"}, "USDC": {"BID": "USDC 7.05", "ASK": "USDC 7.08"}, "PAX": {"BID": "PAX 7.05", "ASK": "PAX 7.07"}, "TUSD": {"BID": "TUSD 7.06", "ASK": "TUSD 7.08"}}}}}